airbender_py_client/__init__.py
airbender_py_client/client.py
airbender_py_client/provider_registry.py
airbender_py_client/py.typed
airbender_py_client/store.py
airbender_py_client/config/__init__.py
airbender_py_client/config/config.py
airbender_py_client/http/__init__.py
airbender_py_client/http/client.py
airbender_py_client/models/__init__.py
airbender_py_client/models/base.py
airbender_py_client/models/message.py
airbender_py_client/models/session.py
airbender_py_google/__init__.py
airbender_py_google/provider.py
airbender_py_google/py.typed
airbender_py_google-0.2.12.dist-info/METADATA
airbender_py_google-0.2.12.dist-info/WHEEL
airbender_py_google-0.2.12.dist-info/RECORD
