Metadata-Version: 2.4
Name: airbender-py-google
Version: 0.2.12
Summary: Google Generative AI provider for Airbender Python SDK
Author-email: "Rangle.io" <info@rangle.io>
License: Apache-2.0
Requires-Python: >=3.12
Requires-Dist: annotated-types==0.7.0
Requires-Dist: anyio==4.9.0
Requires-Dist: cachetools==5.5.2
Requires-Dist: certifi==2025.6.15
Requires-Dist: charset-normalizer==3.4.2
Requires-Dist: colorama==0.4.6; sys_platform == 'win32'
Requires-Dist: google-ai-generativelanguage==0.6.15
Requires-Dist: google-api-core==2.25.1
Requires-Dist: google-api-python-client==2.172.0
Requires-Dist: google-auth-httplib2==0.2.0
Requires-Dist: google-auth==2.40.3
Requires-Dist: google-generativeai==0.8.5
Requires-Dist: googleapis-common-protos==1.70.0
Requires-Dist: grpcio-status==1.71.0
Requires-Dist: grpcio==1.73.0
Requires-Dist: h11==0.16.0
Requires-Dist: httpcore==1.0.9
Requires-Dist: httplib2==0.22.0
Requires-Dist: httpx==0.28.1
Requires-Dist: idna==3.10
Requires-Dist: iniconfig==2.1.0
Requires-Dist: mypy-extensions==1.1.0
Requires-Dist: mypy==1.16.1
Requires-Dist: packaging==24.2
Requires-Dist: pathspec==0.12.1
Requires-Dist: pluggy==1.6.0
Requires-Dist: proto-plus==1.26.1
Requires-Dist: protobuf==5.29.5
Requires-Dist: pyasn1-modules==0.4.2
Requires-Dist: pyasn1==0.6.1
Requires-Dist: pydantic-core==2.33.2
Requires-Dist: pydantic==2.11.7
Requires-Dist: pygments==2.19.1
Requires-Dist: pyparsing==3.2.3
Requires-Dist: pytest-asyncio==1.0.0
Requires-Dist: pytest-httpx==0.35.0
Requires-Dist: pytest==8.4.0
Requires-Dist: python-dotenv==1.1.0
Requires-Dist: requests==2.32.4
Requires-Dist: rsa==4.9.1
Requires-Dist: ruff==0.11.13
Requires-Dist: sniffio==1.3.1
Requires-Dist: tqdm==4.67.1
Requires-Dist: typing-extensions==4.14.0
Requires-Dist: typing-inspection==0.4.1
Requires-Dist: uritemplate==4.2.0
Requires-Dist: urllib3==2.4.0
Provides-Extra: dev
Requires-Dist: mypy; extra == 'dev'
Requires-Dist: pytest; extra == 'dev'
Requires-Dist: pytest-asyncio; extra == 'dev'
Requires-Dist: pytest-httpx; extra == 'dev'
Requires-Dist: ruff; extra == 'dev'
